cnvizard/__init__.py
cnvizard/app.py
cnvizard/exporter.py
cnvizard/helpers.py
cnvizard/omim.py
cnvizard/plotter.py
cnvizard/reference_processing.py
cnvizard/run.py
cnvizard/styler.py
cnvizard/vcf_Merger.py
cnvizard/visualizer.py
cnvizard/resources/__init__.py
cnvizard/resources/annotsv_format.txt
cnvizard/resources/candidate_lists/cardiac_rythm_disorders.txt
cnvizard/resources/candidate_lists/cardiomyopathy.txt
cnvizard/resources/candidate_lists/cholestasis.txt
cnvizard/resources/candidate_lists/coagulation_disorders.txt
cnvizard/resources/candidate_lists/dementia.txt
cnvizard/resources/candidate_lists/eds_mfs.txt
cnvizard/resources/candidate_lists/enthrocyte_disorders.txt
cnvizard/resources/candidate_lists/epilepsy.txt
cnvizard/resources/candidate_lists/fever_disorders.txt
cnvizard/resources/candidate_lists/hearing_loss.txt
cnvizard/resources/candidate_lists/hematological_disorders.txt
cnvizard/resources/candidate_lists/imprinting_disorders.txt
cnvizard/resources/candidate_lists/intellectual_disability.txt
cnvizard/resources/candidate_lists/leukoencephalopathy.txt
cnvizard/resources/candidate_lists/microcephaly.txt
cnvizard/resources/candidate_lists/neuromuscular_disorders.txt
cnvizard/resources/candidate_lists/pancreatitis.txt
cnvizard/resources/candidate_lists/rasopathies.txt
cnvizard/resources/candidate_lists/retinopathy.txt
cnvizard/resources/candidate_lists/skeletal_dysplasia.txt
cnvizard/resources/candidate_lists/tumors.txt
cnvizard/resources/candidate_lists/vascular_cognitive_impairment_dementia.txt
cnvizard/resources/candidate_lists/zn.txt
cnvizard/resources/references/bintest_ref.parquet
cnvizard/resources/references/exome_cnv_reference_bintest_large.parquet
cnvizard/resources/references/exome_cnv_reference_large.parquet
cnvizard/resources/references/genome_cnv_reference_bintest_large.parquet
cnvizard/resources/references/genome_cnv_reference_large.parquet
cnvizard/resources/references/total_ref.parquet
cnvizard-0.3.1.dist-info/LICENSE
cnvizard-0.3.1.dist-info/METADATA
cnvizard-0.3.1.dist-info/WHEEL
cnvizard-0.3.1.dist-info/entry_points.txt
cnvizard-0.3.1.dist-info/top_level.txt
cnvizard-0.3.1.dist-info/RECORD
