Metadata-Version: 2.1
Name: cnvizard
Version: 0.3.1
Summary: A tool for visualizing germline copy number variants
Home-page: https://github.com/IHGGM-Aachen/CNVizard
Author: Jeremias Krause, Carlos Classen, Matthias Begemann, Florian Kraft
Author-email: jerkrause@ukaachen.de
Classifier: Programming Language :: Python :: 3
Classifier: License :: OSI Approved :: MIT License
Classifier: Operating System :: OS Independent
Requires-Python: >=3.12.4
License-File: LICENSE
Requires-Dist: streamlit
Requires-Dist: pandas
Requires-Dist: numpy
Requires-Dist: pyarrow
Requires-Dist: fastparquet
Requires-Dist: plotly
Requires-Dist: python-dotenv
Requires-Dist: xlsxwriter
Requires-Dist: seaborn
Requires-Dist: cyvcf2
Requires-Dist: pillow
